stuphmud/__init__.py
stuphmud/elemental.py
stuphmud/server/__init__.py
stuphmud/server/adapters.py
stuphmud/server/api/__init__.py
stuphmud/server/api/constants.py
stuphmud/server/api/structs.py
stuphmud/server/api/tests.py
stuphmud/server/magic/__init__.py
stuphmud/server/magic/structure.py
stuphmud/server/player/__init__.py
stuphmud/server/player/editor.py
stuphmud/server/player/events.py
stuphmud/server/player/http.py
stuphmud/server/player/notebook.py
stuphmud/server/player/shell.py
stuphmud/server/player/commands/__init__.py
stuphmud/server/player/commands/mime.py
stuphmud/server/player/commands/gc/__init__.py
stuphmud/server/player/commands/gc/olc.py
stuphmud/server/player/commands/gc/profiling.py
stuphmud/server/player/commands/gc/system.py
stuphmud/server/player/commands/gc/web_debug.py
stuphmud/server/player/commands/gc/wizard.py
stuphmud/server/player/commands/gc/xdebug.py
stuphmud/server/player/db/__init__.py
stuphmud/server/player/db/hi.py
stuphmud/server/player/db/managedfs.py
stuphmud/server/player/db/playerfile.py
stuphmud/server/player/db/sql.py
stuphmud/server/player/db/rent/__init__.py
stuphmud/server/player/db/rent/constants.py
stuphmud/server/player/db/rent/edit.py
stuphmud/server/player/db/rent/equip.py
stuphmud/server/player/db/rent/management.py
stuphmud/server/player/db/rent/scan.py
stuphmud/server/player/db/rent/show.py
stuphmud/server/player/interfaces/__init__.py
stuphmud/server/player/interfaces/dictcmd.py
stuphmud/server/player/interfaces/history.py
stuphmud/server/player/interfaces/standard.py
stuphmud/server/player/interfaces/threading.py
stuphmud/server/player/interfaces/code/__init__.py
stuphmud/server/player/interfaces/code/environ.py
stuphmud/server/player/interfaces/code/girl.py
stuphmud/server/player/interfaces/code/python.py
stuphmud/server/player/interfaces/code/xmlrpc_python.py
stuphmud/server/player/messaging/__init__.py
stuphmud/server/player/telnet/__init__.py
stuphmud/server/player/telnet/client.py
stuphos-2.0.7.dist-info/METADATA
stuphos-2.0.7.dist-info/WHEEL
stuphos-2.0.7.dist-info/top_level.txt
stuphos-2.0.7.dist-info/RECORD
